{
  "id": "process",
  "type": "SharedSlice",
  "name": "Process",
  "description": "Process",
  "variations": [
    {
      "id": "default",
      "name": "Default",
      "docURL": "...",
      "version": "initial",
      "description": "Default",
      "imageUrl": "",
      "primary": {
        "badge": {
          "type": "Text",
          "config": {
            "label": "Badge",
            "placeholder": ""
          }
        },
        "title": {
          "type": "StructuredText",
          "config": {
            "label": "Title",
            "placeholder": "",
            "allowTargetBlank": true,
            "multi": "heading2,strong"
          }
        },
        "description": {
          "type": "StructuredText",
          "config": {
            "label": "Description",
            "placeholder": "",
            "allowTargetBlank": true,
            "multi": "paragraph"
          }
        },
        "image": {
          "type": "Image",
          "config": {
            "label": "Image",
            "constraint": {},
            "thumbnails": []
          }
        },
        "steps": {
          "type": "Group",
          "config": {
            "label": "Steps",
            "repeat": true,
            "fields": {
              "icon": {
                "type": "Select",
                "config": {
                  "label": "Icon",
                  "placeholder": "",
                  "options": [
                    "messageCircleMore",
                    "penTool",
                    "code2",
                    "rocket"
                  ]
                }
              },
              "text": {
                "type": "StructuredText",
                "config": {
                  "label": "Text",
                  "placeholder": "",
                  "allowTargetBlank": true,
                  "multi": "heading3"
                }
              },
              "subtext": {
                "type": "StructuredText",
                "config": {
                  "label": "Subtext",
                  "placeholder": "",
                  "allowTargetBlank": true,
                  "multi": "paragraph"
                }
              }
            }
          }
        }
      },
      "items": {}
    }
  ]
}